pydevmgr_ua/__init__.py
pydevmgr_ua/config.py
pydevmgr_ua/register.py
pydevmgr_ua/uabase.py
pydevmgr_ua/uacom.py
pydevmgr_ua/uadevice.py
pydevmgr_ua/uaengine.py
pydevmgr_ua/uainterface.py
pydevmgr_ua/uanode.py
pydevmgr_ua/uarpc.py
pydevmgr_ua/variants.py
pydevmgr_ua-0.6a6.dist-info/WHEEL
pydevmgr_ua-0.6a6.dist-info/METADATA
pydevmgr_ua-0.6a6.dist-info/RECORD
