Metadata-Version: 2.1
Name: pydevmgr-ua
Version: 0.6a6
Summary: pydevmgr plugin to handle opc-ua communication
License: CECILL-2.1
Author: Sylvain Guieu
Author-email: sylvain.guieu@univ-grenoble-alpes.fr
Requires-Python: >=3.7,<4.0
Classifier: License :: OSI Approved :: CEA CNRS Inria Logiciel Libre License, version 2.1 (CeCILL-2.1)
Classifier: Programming Language :: Python :: 3
Classifier: Programming Language :: Python :: 3.7
Classifier: Programming Language :: Python :: 3.8
Classifier: Programming Language :: Python :: 3.9
Classifier: Programming Language :: Python :: 3.10
Classifier: Programming Language :: Python :: 3.11
Requires-Dist: cryptography (>=39.0.0,<40.0.0)
Requires-Dist: opcua (>=0.98.13,<0.99.0)
Requires-Dist: pydevmgr-core (>=0.6.a4)
